commands/__init__.py
commands/cli.py
commands/templates/mvc/app/app.py
commands/templates/mvc/app/assets/favicon.png
commands/templates/mvc/app/assets/icon.png
commands/templates/mvc/app/assets/manifest.json
commands/templates/mvc/app/assets/icons/icon-192.png
commands/templates/mvc/app/assets/icons/icon-512.png
commands/templates/mvc/app/assets/icons/icon-maskable-19.png
commands/templates/mvc/app/assets/icons/icon-maskable-512.png
commands/templates/mvc/app/assets/icons/loading-animation.png
commands/templates/mvc/app/assets/icons/loading-animation3.png
commands/templates/mvc/app/controllers/__init__.py
commands/templates/mvc/app/controllers/contador.py
commands/templates/mvc/app/controllers/login.py
commands/templates/mvc/app/models/contador.py
commands/templates/mvc/app/views/__init__.py
commands/templates/mvc/app/views/contador.py
commands/templates/mvc/app/views/index.py
commands/templates/mvc/app/views/login.py
commands/templates/mvc_async/app/app.py
commands/templates/mvc_async/app/assets/favicon.png
commands/templates/mvc_async/app/assets/icon.png
commands/templates/mvc_async/app/assets/manifest.json
commands/templates/mvc_async/app/assets/icons/icon-192.png
commands/templates/mvc_async/app/assets/icons/icon-512.png
commands/templates/mvc_async/app/assets/icons/icon-maskable-19.png
commands/templates/mvc_async/app/assets/icons/icon-maskable-512.png
commands/templates/mvc_async/app/assets/icons/loading-animation.png
commands/templates/mvc_async/app/assets/icons/loading-animation3.png
commands/templates/mvc_async/app/controllers/__init__.py
commands/templates/mvc_async/app/controllers/contador.py
commands/templates/mvc_async/app/controllers/login.py
commands/templates/mvc_async/app/models/contador.py
commands/templates/mvc_async/app/views/__init__.py
commands/templates/mvc_async/app/views/contador.py
commands/templates/mvc_async/app/views/index.py
commands/templates/mvc_async/app/views/login.py
commands/templates/personalized/app/app.py
fast_flet-0.1.1.dist-info/LICENSE
fast_flet-0.1.1.dist-info/METADATA
fast_flet-0.1.1.dist-info/WHEEL
fast_flet-0.1.1.dist-info/entry_points.txt
fast_flet-0.1.1.dist-info/top_level.txt
fast_flet-0.1.1.dist-info/RECORD
